setup.py
gcovparse/__init__.py
gcovparse.egg-info/PKG-INFO
gcovparse.egg-info/SOURCES.txt
gcovparse.egg-info/dependency_links.txt
gcovparse.egg-info/top_level.txt
gcovparse.egg-info/zip-safe