Metadata-Version: 1.1
Name: gcovparse
Version: 0.0.2
Summary: gcov to json
Home-page: http://github.com/codecov/gcov-parse
Author: @codecov
Author-email: hello@codecov.io
License: http://www.apache.org/licenses/LICENSE-2.0
Keywords: coverage
Platform: UNKNOWN
Classifier: Development Status :: 4 - Beta
Classifier: Environment :: Plugins
Classifier: Intended Audience :: Developers
Classifier: License :: OSI Approved :: Apache Software License
Classifier: Topic :: Software Development :: Testing
